crdp.cpython-310-x86_64-linux-gnu.so
crdp_gcp-0.0.4.dist-info/METADATA
crdp_gcp-0.0.4.dist-info/WHEEL
crdp_gcp-0.0.4.dist-info/top_level.txt
crdp_gcp-0.0.4.dist-info/RECORD
crdp_gcp-0.0.4.dist-info/LICENSE.txt
