Metadata-Version: 2.1
Name: crdp-gcp
Version: 0.0.4
Summary: A fast Ramer-Douglas-Peucker algorithm implementation. Updated for GCP cloud function
Home-page: https://github.com/vtecftwy/crdp-gcp
Author: Ran Bi
Author-email: biran0079@gmail.com
License: MIT
Keywords: rdp ramer douglas peucker line simplification cython
Classifier: Programming Language :: Python :: 3
Classifier: License :: OSI Approved :: MIT License
Classifier: Operating System :: OS Independent
License-File: LICENSE.txt
Requires-Dist: cython
Provides-Extra: dev
Requires-Dist: cython ; extra == 'dev'
